pcv/__init__.py
pcv/interact.py
pcv/process.py
pcv/screen.py
pcv/source.py
pcv/vidIO.py
pcv/examples/__init__.py
pcv/examples/cam_video_switch.py
pcv/examples/hand_write.py
pcv/examples/something_fishy.py
pythonic_cv-1.2.2.dist-info/LICENSE
pythonic_cv-1.2.2.dist-info/METADATA
pythonic_cv-1.2.2.dist-info/WHEEL
pythonic_cv-1.2.2.dist-info/top_level.txt
pythonic_cv-1.2.2.dist-info/RECORD
