Metadata-Version: 2.1
Name: pythonic-cv
Version: 1.2.2
Summary: Performant pythonic wrapper of unnecessarily painful opencv functionality
Home-page: https://github.com/ES-Alexander/pythonic-cv
Author: ES-Alexander
Author-email: sandman.esalexander@gmail.com
License: UNKNOWN
Platform: UNKNOWN
Classifier: Programming Language :: Python :: 3
Classifier: License :: OSI Approved :: MIT License
Classifier: Operating System :: OS Independent
Requires-Python: >=3.6
License-File: LICENSE
